Metadata-Version: 1.0
Name: a8e
Version: 0.1
Summary: a8e is `a8e abbreviate`
Home-page: http://k0s.org/hg/a8e
Author: Jeff Hammel
Author-email: k0scist@gmail.com
License: UNKNOWN
Platform: UNKNOWN
